MANIFEST.in
README.rst
setup.py
beeflow/__init__.py
beeflow/frame.py
beeflow.egg-info/PKG-INFO
beeflow.egg-info/SOURCES.txt
beeflow.egg-info/dependency_links.txt
beeflow.egg-info/requires.txt
beeflow.egg-info/top_level.txt
beeflow/beelo/__init__.py
beeflow/beelo/base.py
beeflow/beeman/__init__.py
beeflow/beeman/base.py
beeflow/beeml/__init__.py
beeflow/beeml/base.py
beeflow/beeser/__init__.py
beeflow/beeser/base.py
beeflow/beevi/__init__.py
beeflow/beevi/base.py
beeflow/tutorials/__init__.py
beeflow/tutorials/caching/__init__.py
beeflow/tutorials/caching/flask_caching_test.py
beeflow/tutorials/callback/__init__.py
beeflow/tutorials/callback/chain_input_output.py
beeflow/tutorials/callback/multiple_inputs.py
beeflow/tutorials/callback/multiple_outputs.py
beeflow/tutorials/callback/slider_graph.py
beeflow/tutorials/callback/textbox.py
beeflow/tutorials/interactive/__init__.py
beeflow/tutorials/interactive/attributes.py
beeflow/tutorials/interactive/crossfilter.py
beeflow/tutorials/interactive/graphs_hover.py
beeflow/tutorials/layout/__init__.py
beeflow/tutorials/layout/core_components.py
beeflow/tutorials/layout/dcc_graph.py
beeflow/tutorials/layout/go_table.py
beeflow/tutorials/layout/hello_dash.py
beeflow/tutorials/layout/html_table.py
beeflow/tutorials/sharingdata/__init__.py
beeflow/tutorials/sharingdata/caching.py
beeflow/tutorials/state/__init__.py
beeflow/tutorials/state/state.py
beeflow/tutorials/tabs/__init__.py
beeflow/tutorials/tabs/tabs.py