Metadata-Version: 1.1
Name: beeflow
Version: 0.0.2
Summary: BeeML
Home-page: UNKNOWN
Author: Dae-Won Kim
Author-email: dwkim78@gmail.com
License: Apache v2.0
Platform: any
Classifier: Operating System :: OS Independent
Classifier: Programming Language :: Python :: 3.5
Classifier: Topic :: Scientific/Engineering :: Artificial Intelligence
